myhelloya/__init__.py
myhelloya/moudle1.py
myhelloya-0.1.0.dist-info/METADATA
myhelloya-0.1.0.dist-info/WHEEL
myhelloya-0.1.0.dist-info/RECORD
