Metadata-Version: 2.1
Name: myhelloya
Version: 0.1.0
Summary: mlyl的第一个上传脚本
Author: mlyl
Requires-Python: ==3.8.2
Classifier: Programming Language :: Python :: 3
